{"cameraMode":{"drawMode":0,"name":"Shaded","section":"Shading Mode"},"sceneLighting":true,"audioPlay":false,"sceneViewState":{"m_AlwaysRefresh":false,"showFog":true,"showSkybox":true,"showFlares":true,"showImageEffects":true,"showParticleSystems":true,"showVisualEffectGraphs":true,"m_FxEnabled":false},"in2DMode":false,"pivot":{"x":-425.7808532714844,"y":-126.09033203125,"z":-11.494270324707032},"rotation":{"x":-0.17381404340267182,"y":0.6149265766143799,"z":-0.14131367206573487,"w":-0.7561305165290833},"size":156.43649291992188,"orthographic":false}